[
  {
    "word_surface": "褒めます",
    "han_viet": "BAO",
    "kana": "ほめます",
    "romaji": "homemasu",
    "tags": [
      "n4",
      "verb",
      "transitive"
    ],
    "pitch_pattern": 3,
    "pitch_svg_path": "M0,20 L25,5 L50,5 L75,20 L100,20",
    "etymology": {
      "parts": [
        {
          "kanji": "褒",
          "han_viet": "BAO",
          "meaning": {
            "vi": "khen ngợi",
            "en": "praise"
          }
        }
      ],
      "note": {
        "vi": "BAO (褒) trong bao thưởng (khen thưởng).",
        "en": "To praise or reward."
      }
    },
    "meanings": {
      "vi": [
        "khen"
      ],
      "en": [
        "praise"
      ]
    },
    "examples": [
      {
        "sentence": "先生に褒められました。",
        "translation": {
          "vi": "Tôi được thầy giáo khen.",
          "en": "I was praised by the teacher."
        }
      }
    ],
    "mnemonic": {
      "vi": "Khen thưởng bao (BAO) la.",
      "en": "Home (Home) run! Everyone praises you."
    },
    "confusions": []
  },
  {
    "word_surface": "しかります",
    "han_viet": "SẤT",
    "kana": "しかります",
    "romaji": "shikarimasu",
    "tags": [
      "n4",
      "verb",
      "transitive"
    ],
    "pitch_pattern": 3,
    "pitch_svg_path": "M0,20 L25,5 L50,5 L75,20 L100,20",
    "etymology": {
      "parts": [
        {
          "kanji": "叱",
          "han_viet": "SẤT",
          "meaning": {
            "vi": "la mắng",
            "en": "scold"
          }
        }
      ],
      "note": {
        "vi": "SẤT (叱) là quát mắng.",
        "en": "To scold."
      }
    },
    "meanings": {
      "vi": [
        "mắng",
        "la mắng"
      ],
      "en": [
        "scold"
      ]
    },
    "examples": [
      {
        "sentence": "母にしかられました。",
        "translation": {
          "vi": "Tôi bị mẹ mắng.",
          "en": "I was scolded by my mother."
        }
      }
    ],
    "mnemonic": {
      "vi": "Bị quát SẤT vào mặt.",
      "en": "She carries (Shikari) anger when she scolds."
    },
    "confusions": []
  },
  {
    "word_surface": "誘います",
    "han_viet": "DỤ",
    "kana": "さそいます",
    "romaji": "sasoimasu",
    "tags": [
      "n4",
      "verb",
      "transitive"
    ],
    "pitch_pattern": 3,
    "pitch_svg_path": "M0,20 L25,5 L50,5 L75,20 L100,20",
    "etymology": {
      "parts": [
        {
          "kanji": "誘",
          "han_viet": "DỤ",
          "meaning": {
            "vi": "mời mọc/dụ dỗ",
            "en": "invite/entice"
          }
        }
      ],
      "note": {
        "vi": "DỤ (誘) trong dụ dỗ, quyến rũ. Ở đây nghĩa tốt là mời rủ.",
        "en": "To invite or entice."
      }
    },
    "meanings": {
      "vi": [
        "mời",
        "rủ rê"
      ],
      "en": [
        "invite",
        "ask someone out"
      ]
    },
    "examples": [
      {
        "sentence": "友達を映画に誘いました。",
        "translation": {
          "vi": "Tôi rủ bạn đi xem phim.",
          "en": "I invited my friend to a movie."
        }
      }
    ],
    "mnemonic": {
      "vi": "DỤ dỗ bạn đi chơi.",
      "en": "Sass (Saso) me and I won't invite you."
    },
    "confusions": [
      {
        "word": "招待します",
        "explanation": {
          "mnemonic": {
            "vi": "Sasoimasu là rủ rê thân mật. Shoutaishimasu là chiêu đãi, mời trang trọng.",
            "en": "Sasou is casual inviting. Shoutai is formal invitation."
          },
          "item1_nuance": {
            "vi": "Rủ cùng làm gì đó (thân mật).",
            "en": "Invite to join (casual)."
          },
          "item2_nuance": {
            "vi": "Mời đến dự tiệc/sự kiện (trang trọng).",
            "en": "Formal invitation to an event."
          }
        }
      }
    ]
  },
  {
    "word_surface": "招待します",
    "han_viet": "CHIÊU ĐÃI",
    "kana": "しょうたいします",
    "romaji": "shoutaishimasu",
    "tags": [
      "n4",
      "verb",
      "suru-verb"
    ],
    "pitch_pattern": 3,
    "pitch_svg_path": "M0,20 L25,5 L50,5 L75,5 L100,20 L125,20",
    "etymology": {
      "parts": [
        {
          "kanji": "招",
          "han_viet": "CHIÊU",
          "meaning": {
            "vi": "vẫy gọi",
            "en": "beckon"
          }
        },
        {
          "kanji": "待",
          "han_viet": "ĐÃI",
          "meaning": {
            "vi": "chờ đợi/đối đãi",
            "en": "treat/wait"
          }
        }
      ],
      "note": {
        "vi": "CHIÊU ĐÃI (招待) là mời đến để tiếp đãi.",
        "en": "Invitation."
      }
    },
    "meanings": {
      "vi": [
        "mời",
        "chiêu đãi"
      ],
      "en": [
        "invite"
      ]
    },
    "examples": [
      {
        "sentence": "誕生日のパーティーに招待されました。",
        "translation": {
          "vi": "Tôi được mời đến tiệc sinh nhật.",
          "en": "I was invited to a birthday party."
        }
      }
    ],
    "mnemonic": {
      "vi": "CHIÊU ĐÃI khách quý.",
      "en": "Show time (Shoutai)! You are invited."
    },
    "confusions": []
  },
  {
    "word_surface": "頼みます",
    "han_viet": "LẠI",
    "kana": "たのみます",
    "romaji": "tanomimasu",
    "tags": [
      "n4",
      "verb",
      "transitive"
    ],
    "pitch_pattern": 3,
    "pitch_svg_path": "M0,20 L25,5 L50,5 L75,20 L100,20",
    "etymology": {
      "parts": [
        {
          "kanji": "頼",
          "han_viet": "LẠI",
          "meaning": {
            "vi": "nhờ cậy/ỷ lại",
            "en": "rely"
          }
        }
      ],
      "note": {
        "vi": "LẠI (頼) trong ỷ lại, tin cậy.",
        "en": "To request or rely on."
      }
    },
    "meanings": {
      "vi": [
        "nhờ",
        "yêu cầu"
      ],
      "en": [
        "ask",
        "request"
      ]
    },
    "examples": [
      {
        "sentence": "母に買い物を頼まれました。",
        "translation": {
          "vi": "Tôi bị mẹ nhờ đi mua đồ.",
          "en": "I was asked by my mother to go shopping."
        }
      }
    ],
    "mnemonic": {
      "vi": "Ỷ LẠI vào người khác là cứ nhờ vả mãi.",
      "en": "Tan (Tano) no more (mimasu)! Stop asking me."
    },
    "confusions": []
  },
  {
    "word_surface": "注意します",
    "han_viet": "CHÚ Ý",
    "kana": "ちゅういします",
    "romaji": "chuuishimasu",
    "tags": [
      "n4",
      "verb",
      "suru-verb"
    ],
    "pitch_pattern": 3,
    "pitch_svg_path": "M0,20 L25,5 L50,5 L75,5 L100,20 L125,20",
    "etymology": {
      "parts": [
        {
          "kanji": "注",
          "han_viet": "CHÚ",
          "meaning": {
            "vi": "rót/tập trung",
            "en": "pour/concentrate"
          }
        },
        {
          "kanji": "意",
          "han_viet": "Ý",
          "meaning": {
            "vi": "ý chí/tâm ý",
            "en": "mind"
          }
        }
      ],
      "note": {
        "vi": "CHÚ Ý là dồn tâm trí vào việc gì đó.",
        "en": "Pouring one's mind into something = Caution/Attention."
      }
    },
    "meanings": {
      "vi": [
        "chú ý",
        "nhắc nhở"
      ],
      "en": [
        "warn",
        "pay attention"
      ]
    },
    "examples": [
      {
        "sentence": "車に注意してください。",
        "translation": {
          "vi": "Hãy chú ý xe ô tô.",
          "en": "Please watch out for cars."
        }
      }
    ],
    "mnemonic": {
      "vi": "CHÚ Ý.",
      "en": "Chew (Chuu) lightly... pay attention!"
    },
    "confusions": []
  },
  {
    "word_surface": "とります",
    "han_viet": "THỦ",
    "kana": "とります",
    "romaji": "torimasu",
    "tags": [
      "n4",
      "verb",
      "transitive"
    ],
    "pitch_pattern": 3,
    "pitch_svg_path": "M0,20 L25,5 L50,5 L75,20 L100,20",
    "etymology": {
      "parts": [
        {
          "kanji": "取",
          "han_viet": "THỦ",
          "meaning": {
            "vi": "lấy",
            "en": "take"
          }
        }
      ],
      "note": {
        "vi": "THỦ (取) là lấy. Ở bài này nghĩa là lấy trộm (ăn cắp).",
        "en": "To take (steal)."
      }
    },
    "meanings": {
      "vi": [
        "lấy trộm",
        "ăn cắp"
      ],
      "en": [
        "steal",
        "rob"
      ]
    },
    "examples": [
      {
        "sentence": "財布をとられました。",
        "translation": {
          "vi": "Tôi bị lấy trộm ví.",
          "en": "My wallet was stolen."
        }
      }
    ],
    "mnemonic": {
      "vi": "Kẻ gian THỦ (lấy) mất đồ.",
      "en": "Tory (Tori) took my money."
    },
    "confusions": []
  },
  {
    "word_surface": "踏みます",
    "han_viet": "ĐẠP",
    "kana": "ふみます",
    "romaji": "fumimasu",
    "tags": [
      "n4",
      "verb",
      "transitive"
    ],
    "pitch_pattern": 3,
    "pitch_svg_path": "M0,20 L25,5 L50,5 L75,20 L100,20",
    "etymology": {
      "parts": [
        {
          "kanji": "踏",
          "han_viet": "ĐẠP",
          "meaning": {
            "vi": "giẫm lên",
            "en": "step on"
          }
        }
      ],
      "note": {
        "vi": "ĐẠP (踏) là giẫm chân lên.",
        "en": "To step on."
      }
    },
    "meanings": {
      "vi": [
        "giẫm",
        "đạp lên"
      ],
      "en": [
        "step on"
      ]
    },
    "examples": [
      {
        "sentence": "足を踏まれました。",
        "translation": {
          "vi": "Tôi bị giẫm lên chân.",
          "en": "My foot was stepped on."
        }
      }
    ],
    "mnemonic": {
      "vi": "ĐẠP lên chân người khác là bất lịch sự.",
      "en": "Who (Fu) stepped on me (mi)?"
    },
    "confusions": []
  },
  {
    "word_surface": "壊します",
    "han_viet": "HOẠI",
    "kana": "こわします",
    "romaji": "kowashimasu",
    "tags": [
      "n4",
      "verb",
      "transitive"
    ],
    "pitch_pattern": 4,
    "pitch_svg_path": "M0,20 L25,5 L50,5 L75,5 L100,20",
    "etymology": {
      "parts": [
        {
          "kanji": "壊",
          "han_viet": "HOẠI",
          "meaning": {
            "vi": "hư hỏng/phá",
            "en": "break"
          }
        }
      ],
      "note": {
        "vi": "HOẠI (壊) trong hủy hoại, phá hoại.",
        "en": "To break or destroy."
      }
    },
    "meanings": {
      "vi": [
        "làm hỏng",
        "phá hoại"
      ],
      "en": [
        "break",
        "destroy"
      ]
    },
    "examples": [
      {
        "sentence": "弟に時計を壊されました。",
        "translation": {
          "vi": "Tôi bị em trai làm hỏng đồng hồ.",
          "en": "My watch was broken by my younger brother."
        }
      }
    ],
    "mnemonic": {
      "vi": "Phá HOẠI đồ đạc.",
      "en": "Cow (Kowa) broke the fence."
    },
    "confusions": []
  },
  {
    "word_surface": "汚します",
    "han_viet": "Ô",
    "kana": "よごします",
    "romaji": "yogoshimasu",
    "tags": [
      "n4",
      "verb",
      "transitive"
    ],
    "pitch_pattern": 3,
    "pitch_svg_path": "M0,20 L25,5 L50,5 L75,20 L100,20",
    "etymology": {
      "parts": [
        {
          "kanji": "汚",
          "han_viet": "Ô",
          "meaning": {
            "vi": "bẩn",
            "en": "dirty"
          }
        }
      ],
      "note": {
        "vi": "Ô (汚) trong ô nhiễm, ô uế.",
        "en": "To make dirty."
      }
    },
    "meanings": {
      "vi": [
        "làm bẩn"
      ],
      "en": [
        "make dirty",
        "soil"
      ]
    },
    "examples": [
      {
        "sentence": "服を汚しました。",
        "translation": {
          "vi": "Tôi làm bẩn quần áo.",
          "en": "I soiled my clothes."
        }
      }
    ],
    "mnemonic": {
      "vi": "Ô nhiễm làm bẩn môi trường.",
      "en": "Yo, go (Yogo) wash it, you made it dirty."
    },
    "confusions": []
  },
  {
    "word_surface": "行います",
    "han_viet": "HÀNH",
    "kana": "おこないます",
    "romaji": "okonaimasu",
    "tags": [
      "n4",
      "verb",
      "transitive"
    ],
    "pitch_pattern": 5,
    "pitch_svg_path": "M0,20 L25,5 L50,5 L75,5 L100,5 L125,20",
    "etymology": {
      "parts": [
        {
          "kanji": "行",
          "han_viet": "HÀNH",
          "meaning": {
            "vi": "đi/làm",
            "en": "do/act"
          }
        }
      ],
      "note": {
        "vi": "HÀNH (行) trong thực hành, tiến hành.",
        "en": "To conduct or carry out."
      }
    },
    "meanings": {
      "vi": [
        "tổ chức",
        "tiến hành"
      ],
      "en": [
        "hold",
        "carry out"
      ]
    },
    "examples": [
      {
        "sentence": "会議を行います。",
        "translation": {
          "vi": "Tiến hành cuộc họp.",
          "en": "Hold a meeting."
        }
      }
    ],
    "mnemonic": {
      "vi": "Tiến HÀNH công việc.",
      "en": "Oh, coconut (Okona) festival is being held today."
    },
    "confusions": []
  },
  {
    "word_surface": "輸出します",
    "han_viet": "THÂU XUẤT",
    "kana": "ゆしゅつします",
    "romaji": "yushutsushimasu",
    "tags": [
      "n4",
      "verb",
      "suru-verb"
    ],
    "pitch_pattern": 3,
    "pitch_svg_path": "M0,20 L25,5 L50,5 L75,5 L100,20",
    "etymology": {
      "parts": [
        {
          "kanji": "輸",
          "han_viet": "THÂU",
          "meaning": {
            "vi": "vận chuyển",
            "en": "transport"
          }
        },
        {
          "kanji": "出",
          "han_viet": "XUẤT",
          "meaning": {
            "vi": "ra",
            "en": "out"
          }
        }
      ],
      "note": {
        "vi": "THÂU XUẤT (輸出) là vận chuyển ra ngoài nước (xuất khẩu).",
        "en": "Transport out -> Export."
      }
    },
    "meanings": {
      "vi": [
        "xuất khẩu"
      ],
      "en": [
        "export"
      ]
    },
    "examples": [
      {
        "sentence": "日本は車を輸出しています。",
        "translation": {
          "vi": "Nhật Bản xuất khẩu xe hơi.",
          "en": "Japan exports cars."
        }
      }
    ],
    "mnemonic": {
      "vi": "THÂU XUẤT hàng hóa.",
      "en": "You shoot (Yushuutsu) goods out to other countries."
    },
    "confusions": []
  },
  {
    "word_surface": "輸入します",
    "han_viet": "THÂU NHẬP",
    "kana": "ゆにゅうします",
    "romaji": "yunyuushimasu",
    "tags": [
      "n4",
      "verb",
      "suru-verb"
    ],
    "pitch_pattern": 3,
    "pitch_svg_path": "M0,20 L25,5 L50,5 L75,5 L100,20",
    "etymology": {
      "parts": [
        {
          "kanji": "輸",
          "han_viet": "THÂU",
          "meaning": {
            "vi": "vận chuyển",
            "en": "transport"
          }
        },
        {
          "kanji": "入",
          "han_viet": "NHẬP",
          "meaning": {
            "vi": "vào",
            "en": "in"
          }
        }
      ],
      "note": {
        "vi": "THÂU NHẬP (輸入) là vận chuyển vào trong nước (nhập khẩu).",
        "en": "Transport in -> Import."
      }
    },
    "meanings": {
      "vi": [
        "nhập khẩu"
      ],
      "en": [
        "import"
      ]
    },
    "examples": [
      {
        "sentence": "石油を輸入します。",
        "translation": {
          "vi": "Nhập khẩu dầu mỏ.",
          "en": "Import oil."
        }
      }
    ],
    "mnemonic": {
      "vi": "THÂU NHẬP hàng hóa.",
      "en": "You new (Yunyuu)? Welcome in (Import)."
    },
    "confusions": []
  },
  {
    "word_surface": "翻訳します",
    "han_viet": "PHIÊN DỊCH",
    "kana": "ほんやくします",
    "romaji": "honyakushimasu",
    "tags": [
      "n4",
      "verb",
      "suru-verb"
    ],
    "pitch_pattern": 3,
    "pitch_svg_path": "M0,20 L25,5 L50,5 L75,5 L100,20",
    "etymology": {
      "parts": [
        {
          "kanji": "翻",
          "han_viet": "PHIÊN",
          "meaning": {
            "vi": "lật/phiên",
            "en": "flip/translate"
          }
        },
        {
          "kanji": "訳",
          "han_viet": "DỊCH",
          "meaning": {
            "vi": "dịch",
            "en": "translation"
          }
        }
      ],
      "note": {
        "vi": "PHIÊN DỊCH (翻訳) là dịch văn bản (biên dịch).",
        "en": "Translation (written)."
      }
    },
    "meanings": {
      "vi": [
        "biên dịch",
        "dịch (sách, tài liệu)"
      ],
      "en": [
        "translate"
      ]
    },
    "examples": [
      {
        "sentence": "小説を翻訳します。",
        "translation": {
          "vi": "Dịch tiểu thuyết.",
          "en": "Translate a novel."
        }
      }
    ],
    "mnemonic": {
      "vi": "PHIÊN DỊCH sách.",
      "en": "Hone (Hon) your yak (yaku) translation skills."
    },
    "confusions": []
  },
  {
    "word_surface": "発明します",
    "han_viet": "PHÁT MINH",
    "kana": "はつめいします",
    "romaji": "hatsumeishimasu",
    "tags": [
      "n4",
      "verb",
      "suru-verb"
    ],
    "pitch_pattern": 0,
    "pitch_svg_path": "M0,20 L25,5 L50,5 L75,5 L100,5 L125,5",
    "etymology": {
      "parts": [
        {
          "kanji": "発",
          "han_viet": "PHÁT",
          "meaning": {
            "vi": "phát ra",
            "en": "emit"
          }
        },
        {
          "kanji": "明",
          "han_viet": "MINH",
          "meaning": {
            "vi": "sáng",
            "en": "bright"
          }
        }
      ],
      "note": {
        "vi": "PHÁT MINH ra cái mới.",
        "en": "Invention."
      }
    },
    "meanings": {
      "vi": [
        "phát minh"
      ],
      "en": [
        "invent"
      ]
    },
    "examples": [
      {
        "sentence": "電話発明したのは誰ですか。",
        "translation": {
          "vi": "Ai là người phát minh ra điện thoại?",
          "en": "Who invented the telephone?"
        }
      }
    ],
    "mnemonic": {
      "vi": "PHÁT MINH.",
      "en": "Hats (Hatsu) may (mei) be a great invention."
    },
    "confusions": []
  },
  {
    "word_surface": "発見します",
    "han_viet": "PHÁT KIẾN",
    "kana": "はっけんします",
    "romaji": "hakkenshimasu",
    "tags": [
      "n4",
      "verb",
      "suru-verb"
    ],
    "pitch_pattern": 0,
    "pitch_svg_path": "M0,20 L25,5 L50,5 L75,5 L100,5",
    "etymology": {
      "parts": [
        {
          "kanji": "発",
          "han_viet": "PHÁT",
          "meaning": {
            "vi": "phát ra",
            "en": "emit"
          }
        },
        {
          "kanji": "見",
          "han_viet": "KIẾN",
          "meaning": {
            "vi": "nhìn thấy",
            "en": "see"
          }
        }
      ],
      "note": {
        "vi": "PHÁT KIẾN (発見) là tìm ra cái đã có mà chưa ai biết (phát hiện).",
        "en": "Discovery."
      }
    },
    "meanings": {
      "vi": [
        "phát hiện",
        "tìm thấy"
      ],
      "en": [
        "discover"
      ]
    },
    "examples": [
      {
        "sentence": "新しい星を発見しました。",
        "translation": {
          "vi": "Đã phát hiện ra ngôi sao mới.",
          "en": "Discovered a new star."
        }
      }
    ],
    "mnemonic": {
      "vi": "PHÁT KIẾN là nhìn thấy lần đầu.",
      "en": "Hack (Hak) can (ken) lead to discovery."
    },
    "confusions": []
  },
  {
    "word_surface": "米",
    "han_viet": "MỄ",
    "kana": "こめ",
    "romaji": "kome",
    "tags": [
      "n4",
      "noun"
    ],
    "pitch_pattern": 2,
    "pitch_svg_path": "M0,20 L25,5",
    "etymology": {
      "parts": [
        {
          "kanji": "米",
          "han_viet": "MỄ",
          "meaning": {
            "vi": "gạo",
            "en": "rice"
          }
        }
      ],
      "note": {
        "vi": "MỄ (米) là hạt gạo.",
        "en": "Rice grain."
      }
    },
    "meanings": {
      "vi": [
        "gạo"
      ],
      "en": [
        "rice (uncooked)"
      ]
    },
    "examples": [
      {
        "sentence": "米を洗います。",
        "translation": {
          "vi": "Vo gạo.",
          "en": "Wash the rice."
        }
      }
    ],
    "mnemonic": {
      "vi": "MỄ là gạo.",
      "en": "Co-met (Kome) lands in a rice field."
    },
    "confusions": []
  },
  {
    "word_surface": "麦",
    "han_viet": "MẠCH",
    "kana": "むぎ",
    "romaji": "mugi",
    "tags": [
      "n4",
      "noun"
    ],
    "pitch_pattern": 1,
    "pitch_svg_path": "M0,5 L25,20",
    "etymology": {
      "parts": [
        {
          "kanji": "麦",
          "han_viet": "MẠCH",
          "meaning": {
            "vi": "lúa mạch",
            "en": "wheat/barley"
          }
        }
      ],
      "note": {
        "vi": "MẠCH (麦) trong lúa mạch.",
        "en": "Wheat or barley."
      }
    },
    "meanings": {
      "vi": [
        "lúa mạch"
      ],
      "en": [
        "barley",
        "wheat"
      ]
    },
    "examples": [
      {
        "sentence": "麦からビールを作ります。",
        "translation": {
          "vi": "Làm bia từ lúa mạch.",
          "en": "Make beer from barley."
        }
      }
    ],
    "mnemonic": {
      "vi": "Lúa MẠCH làm bia.",
      "en": "Moo-gie (Mugi) loves wheat."
    },
    "confusions": []
  },
  {
    "word_surface": "石油",
    "han_viet": "THẠCH DU",
    "kana": "せきゆ",
    "romaji": "sekiyu",
    "tags": [
      "n4",
      "noun"
    ],
    "pitch_pattern": 0,
    "pitch_svg_path": "M0,20 L25,5 L50,5",
    "etymology": {
      "parts": [
        {
          "kanji": "石",
          "han_viet": "THẠCH",
          "meaning": {
            "vi": "đá",
            "en": "stone"
          }
        },
        {
          "kanji": "油",
          "han_viet": "DU",
          "meaning": {
            "vi": "dầu",
            "en": "oil"
          }
        }
      ],
      "note": {
        "vi": "THẠCH DU là dầu từ đá (dầu mỏ).",
        "en": "Oil form stone = Petroleum."
      }
    },
    "meanings": {
      "vi": [
        "dầu mỏ",
        "dầu hỏa"
      ],
      "en": [
        "oil",
        "petroleum"
      ]
    },
    "examples": [
      {
        "sentence": "石油を輸入します。",
        "translation": {
          "vi": "Nhập khẩu dầu mỏ.",
          "en": "Import oil."
        }
      }
    ],
    "mnemonic": {
      "vi": "THẠCH DU là dầu đá.",
      "en": "Say cure (Sekiyu) for energy crisis is oil."
    },
    "confusions": []
  },
  {
    "word_surface": "原料",
    "han_viet": "NGUYÊN LIỆU",
    "kana": "げんりょう",
    "romaji": "genryou",
    "tags": [
      "n4",
      "noun"
    ],
    "pitch_pattern": 3,
    "pitch_svg_path": "M0,20 L25,5 L50,5 L75,5 L100,20",
    "etymology": {
      "parts": [
        {
          "kanji": "原",
          "han_viet": "NGUYÊN",
          "meaning": {
            "vi": "nguồn gốc",
            "en": "origin"
          }
        },
        {
          "kanji": "料",
          "han_viet": "LIỆU",
          "meaning": {
            "vi": "vật liệu",
            "en": "material"
          }
        }
      ],
      "note": {
        "vi": "NGUYÊN LIỆU ban đầu để làm ra sản phẩm.",
        "en": "Raw materials."
      }
    },
    "meanings": {
      "vi": [
        "nguyên liệu"
      ],
      "en": [
        "raw material"
      ]
    },
    "examples": [
      {
        "sentence": "ビールの原料は麦です。",
        "translation": {
          "vi": "Nguyên liệu của bia là lúa mạch.",
          "en": "The raw material for beer is barley."
        }
      }
    ],
    "mnemonic": {
      "vi": "NGUYÊN LIỆU.",
      "en": "Gain real (Genryou) materials."
    },
    "confusions": []
  },
  {
    "word_surface": "インスタントラーメン",
    "han_viet": "",
    "kana": "いんすたんとらーめん",
    "romaji": "insutantoraamen",
    "tags": [
      "n4",
      "noun",
      "katakana"
    ],
    "pitch_pattern": 6,
    "pitch_svg_path": "M0,20 L25,5 L50,5 L75,5 L100,5 L125,5 L150,20",
    "etymology": {
      "parts": [],
      "note": {
        "vi": "Từ mượn tiếng Anh: Instant Ramen.",
        "en": "Instant Ramen."
      }
    },
    "meanings": {
      "vi": [
        "mì ăn liền"
      ],
      "en": [
        "instant noodles"
      ]
    },
    "examples": [
      {
        "sentence": "インスタントラーメンを食べます。",
        "translation": {
          "vi": "Ăn mì gói.",
          "en": "Eat instant noodles."
        }
      }
    ],
    "mnemonic": {
      "vi": "Mì ăn liền.",
      "en": "Instant Ramen."
    },
    "confusions": []
  },
  {
    "word_surface": "デート",
    "han_viet": "",
    "kana": "でーと",
    "romaji": "deeto",
    "tags": [
      "n4",
      "noun",
      "katakana"
    ],
    "pitch_pattern": 1,
    "pitch_svg_path": "M0,5 L25,20 L50,20",
    "etymology": {
      "parts": [],
      "note": {
        "vi": "Từ mượn tiếng Anh: Date.",
        "en": "Date."
      }
    },
    "meanings": {
      "vi": [
        "buổi hẹn hò"
      ],
      "en": [
        "date"
      ]
    },
    "examples": [
      {
        "sentence": "彼女とデートします。",
        "translation": {
          "vi": "Hẹn hò với bạn gái.",
          "en": "Go on a date with girlfriend."
        }
      }
    ],
    "mnemonic": {
      "vi": "Đến (De) chỗ hẹn tô (to).",
      "en": "Date."
    },
    "confusions": []
  },
  {
    "word_surface": "泥棒",
    "han_viet": "NÊ BỔNG",
    "kana": "どろぼう",
    "romaji": "dorobou",
    "tags": [
      "n4",
      "noun"
    ],
    "pitch_pattern": 0,
    "pitch_svg_path": "M0,20 L25,5 L50,5 L75,5",
    "etymology": {
      "parts": [
        {
          "kanji": "泥",
          "han_viet": "NÊ",
          "meaning": {
            "vi": "bùn",
            "en": "mud"
          }
        },
        {
          "kanji": "棒",
          "han_viet": "BỔNG",
          "meaning": {
            "vi": "cái gậy",
            "en": "stick"
          }
        }
      ],
      "note": {
        "vi": "Kẻ trộm thường lấm lem bùn (NÊ) và cầm gậy (BỔNG).",
        "en": "Mud stick = Thief."
      }
    },
    "meanings": {
      "vi": [
        "kẻ trộm"
      ],
      "en": [
        "thief",
        "robber"
      ]
    },
    "examples": [
      {
        "sentence": "泥棒に入られました。",
        "translation": {
          "vi": "Bị kẻ trộm đột nhập.",
          "en": "Broken in by a thief."
        }
      }
    ],
    "mnemonic": {
      "vi": "Kẻ trộm bò (bou) trên đường (doro).",
      "en": "Doro-thy's bow (Dorobou) was stolen by a thief."
    },
    "confusions": []
  },
  {
    "word_surface": "警官",
    "han_viet": "CẢNH QUAN",
    "kana": "けいかん",
    "romaji": "keikan",
    "tags": [
      "n4",
      "noun"
    ],
    "pitch_pattern": 0,
    "pitch_svg_path": "M0,20 L25,5 L50,5 L75,5",
    "etymology": {
      "parts": [
        {
          "kanji": "警",
          "han_viet": "CẢNH",
          "meaning": {
            "vi": "cảnh sát/răn đe",
            "en": "guard"
          }
        },
        {
          "kanji": "官",
          "han_viet": "QUAN",
          "meaning": {
            "vi": "quan chức",
            "en": "official"
          }
        }
      ],
      "note": {
        "vi": "CẢNH QUAN là vị quan cảnh sát.",
        "en": "Police official."
      }
    },
    "meanings": {
      "vi": [
        "cảnh sát"
      ],
      "en": [
        "policeman"
      ]
    },
    "examples": [
      {
        "sentence": "警官に行き方を聞きました。",
        "translation": {
          "vi": "Tôi hỏi đường cảnh sát.",
          "en": "I asked the policeman for directions."
        }
      }
    ],
    "mnemonic": {
      "vi": "CẢNH QUAN.",
      "en": "Kay can (Keikan) become a policeman."
    },
    "confusions": []
  },
  {
    "word_surface": "世界中",
    "han_viet": "THẾ GIỚI TRUNG",
    "kana": "せかいじゅう",
    "romaji": "sekaijuu",
    "tags": [
      "n4",
      "noun",
      "compound"
    ],
    "pitch_pattern": 0,
    "pitch_svg_path": "M0,20 L25,5 L50,5 L75,5 L100,5",
    "etymology": {
      "parts": [
        {
          "kanji": "世",
          "han_viet": "THẾ",
          "meaning": {
            "vi": "thế gian",
            "en": "world"
          }
        },
        {
          "kanji": "界",
          "han_viet": "GIỚI",
          "meaning": {
            "vi": "giới hạn",
            "en": "boundary"
          }
        },
        {
          "kanji": "中",
          "han_viet": "TRUNG",
          "meaning": {
            "vi": "trong/khắp",
            "en": "middle/all over"
          }
        }
      ],
      "note": {
        "vi": "Khắp THẾ GIỚI.",
        "en": "All over the world."
      }
    },
    "meanings": {
      "vi": [
        "khắp thế giới"
      ],
      "en": [
        "all over the world"
      ]
    },
    "examples": [
      {
        "sentence": "世界中を旅行したいです。",
        "translation": {
          "vi": "Tôi muốn đi du lịch khắp thế giới.",
          "en": "I want to travel all over the world."
        }
      }
    ],
    "mnemonic": {
      "vi": "Khắp THẾ GIỚI.",
      "en": "Say kaiju (Sekaijuu) are all over the world."
    },
    "confusions": []
  },
  {
    "word_surface": "何語",
    "han_viet": "HÀ NGỮ",
    "kana": "なにご",
    "romaji": "nanigo",
    "tags": [
      "n5",
      "noun",
      "interrogative"
    ],
    "pitch_pattern": 1,
    "pitch_svg_path": "M0,5 L25,20 L50,20",
    "etymology": {
      "parts": [
        {
          "kanji": "何",
          "han_viet": "HÀ",
          "meaning": {
            "vi": "cái gì",
            "en": "what"
          }
        },
        {
          "kanji": "語",
          "han_viet": "NGỮ",
          "meaning": {
            "vi": "ngôn ngữ",
            "en": "language"
          }
        }
      ],
      "note": {
        "vi": "HÀ NGỮ là tiếng gì.",
        "en": "What language."
      }
    },
    "meanings": {
      "vi": [
        "tiếng gì",
        "ngôn ngữ gì"
      ],
      "en": [
        "what language"
      ]
    },
    "examples": [
      {
        "sentence": "これは何語ですか。",
        "translation": {
          "vi": "Đây là tiếng gì?",
          "en": "What language is this?"
        }
      }
    ],
    "mnemonic": {
      "vi": "HÀ cớ gì không hiểu NGỮ này.",
      "en": "Nani (what) go (language)?"
    },
    "confusions": []
  },
  {
    "word_surface": "誰か",
    "han_viet": "THÙY",
    "kana": "だれか",
    "romaji": "dareka",
    "tags": [
      "n5",
      "pronoun"
    ],
    "pitch_pattern": 1,
    "pitch_svg_path": "M0,5 L25,20 L50,20",
    "etymology": {
      "parts": [
        {
          "kanji": "誰",
          "han_viet": "THÙY",
          "meaning": {
            "vi": "ai",
            "en": "who"
          }
        }
      ],
      "note": {
        "vi": "Dare (ai) + ka (nào đó) = Ai đó.",
        "en": "Who + some = Somebody."
      }
    },
    "meanings": {
      "vi": [
        "ai đó"
      ],
      "en": [
        "somebody",
        "someone"
      ]
    },
    "examples": [
      {
        "sentence": "誰かいますか。",
        "translation": {
          "vi": "Có ai ở đó không?",
          "en": "Is anybody there?"
        }
      }
    ],
    "mnemonic": {
      "vi": "Đã ghê (Dare) cả (ka) người.",
      "en": "Dare (Dare) car (ka) - Whose car?"
    },
    "confusions": []
  },
  {
    "word_surface": "よかったですね",
    "han_viet": "",
    "kana": "よかったですね",
    "romaji": "yokattadesune",
    "tags": [
      "n4",
      "expression",
      "phrase"
    ],
    "pitch_pattern": 2,
    "pitch_svg_path": "M0,20 L25,5 L50,20 L75,20",
    "etymology": {
      "parts": [],
      "note": {
        "vi": "Quá khứ của いい (tốt) + nhé.",
        "en": "Good (past tense)."
      }
    },
    "meanings": {
      "vi": [
        "thế thì tốt quá nhỉ",
        "may quá nhỉ"
      ],
      "en": [
        "That's good",
        "I'm glad"
      ]
    },
    "examples": [
      {
        "sentence": "試験に合格しました。よかったですね。",
        "translation": {
          "vi": "Tôi đỗ kỳ thi rồi. Tốt quá nhỉ.",
          "en": "I passed the exam. That's great."
        }
      }
    ],
    "mnemonic": {
      "vi": "Dô (Yo) cắt (katta) được rồi, tốt quá.",
      "en": "Yo, cutter (Yokatta) worked."
    },
    "confusions": []
  },
  {
    "word_surface": "オリンピック",
    "han_viet": "",
    "kana": "おりんぴっく",
    "romaji": "orinpikku",
    "tags": [
      "n4",
      "noun",
      "katakana"
    ],
    "pitch_pattern": 4,
    "pitch_svg_path": "M0,20 L25,5 L50,5 L75,5 L100,5 L125,20",
    "etymology": {
      "parts": [],
      "note": {
        "vi": "Từ mượn tiếng Anh: Olympic.",
        "en": "Olympic."
      }
    },
    "meanings": {
      "vi": [
        "thế vận hội Olympic"
      ],
      "en": [
        "Olympic Games"
      ]
    },
    "examples": [
      {
        "sentence": "オリンピックに出ます。",
        "translation": {
          "vi": "Tham dự Olympic.",
          "en": "Participate in the Olympics."
        }
      }
    ],
    "mnemonic": {
      "vi": "Olympic.",
      "en": "Olympic."
    },
    "confusions": []
  },
  {
    "word_surface": "ワールドカップ",
    "han_viet": "",
    "kana": "わーるどかっぷ",
    "romaji": "waarudokappu",
    "tags": [
      "n4",
      "noun",
      "katakana"
    ],
    "pitch_pattern": 4,
    "pitch_svg_path": "M0,20 L25,5 L50,5 L75,5 L100,20 L125,20",
    "etymology": {
      "parts": [],
      "note": {
        "vi": "Từ mượn tiếng Anh: World Cup.",
        "en": "World Cup."
      }
    },
    "meanings": {
      "vi": [
        "World Cup",
        "Cúp bóng đá thế giới"
      ],
      "en": [
        "World Cup"
      ]
    },
    "examples": [
      {
        "sentence": "ワールドカップを見ます。",
        "translation": {
          "vi": "Xem World Cup.",
          "en": "Watch the World Cup."
        }
      }
    ],
    "mnemonic": {
      "vi": "World Cup.",
      "en": "World Cup."
    },
    "confusions": []
  },
  {
    "word_surface": "東大寺",
    "han_viet": "ĐÔNG ĐẠI TỰ",
    "kana": "とうだいじ",
    "romaji": "toudaiji",
    "tags": [
      "n4",
      "noun",
      "name"
    ],
    "pitch_pattern": 1,
    "pitch_svg_path": "M0,5 L25,20 L50,20 L75,20",
    "etymology": {
      "parts": [
        {
          "kanji": "東",
          "han_viet": "ĐÔNG",
          "meaning": {
            "vi": "phía đông",
            "en": "east"
          }
        },
        {
          "kanji": "大",
          "han_viet": "ĐẠI",
          "meaning": {
            "vi": "lớn",
            "en": "big"
          }
        },
        {
          "kanji": "寺",
          "han_viet": "TỰ",
          "meaning": {
            "vi": "chùa",
            "en": "temple"
          }
        }
      ],
      "note": {
        "vi": "Chùa lớn ở phía đông.",
        "en": "Great Eastern Temple."
      }
    },
    "meanings": {
      "vi": [
        "Chùa Todaiji"
      ],
      "en": [
        "Todaiji Temple"
      ]
    },
    "examples": [
      {
        "sentence": "東大寺へ行きました。",
        "translation": {
          "vi": "Tôi đã đi chùa Todaiji.",
          "en": "I went to Todaiji Temple."
        }
      }
    ],
    "mnemonic": {
      "vi": "ĐÔNG ĐẠI TỰ.",
      "en": "Toe die G (Toudaiji)."
    },
    "confusions": []
  },
  {
    "word_surface": "大仏",
    "han_viet": "ĐẠI PHẬT",
    "kana": "だいぶつ",
    "romaji": "daibutsu",
    "tags": [
      "n4",
      "noun"
    ],
    "pitch_pattern": 0,
    "pitch_svg_path": "M0,20 L25,5 L50,5 L75,5",
    "etymology": {
      "parts": [
        {
          "kanji": "大",
          "han_viet": "ĐẠI",
          "meaning": {
            "vi": "lớn",
            "en": "big"
          }
        },
        {
          "kanji": "仏",
          "han_viet": "PHẬT",
          "meaning": {
            "vi": "phật",
            "en": "buddha"
          }
        }
      ],
      "note": {
        "vi": "Tượng phật lớn.",
        "en": "Great Buddha."
      }
    },
    "meanings": {
      "vi": [
        "tượng Phật lớn"
      ],
      "en": [
        "Great Buddha"
      ]
    },
    "examples": [
      {
        "sentence": "大仏を見ました。",
        "translation": {
          "vi": "Tôi đã xem tượng Đại Phật.",
          "en": "I saw the Great Buddha."
        }
      }
    ],
    "mnemonic": {
      "vi": "ĐẠI PHẬT to lớn.",
      "en": "Die boots (Daibutsu) are big."
    },
    "confusions": []
  },
  {
    "word_surface": "江戸時代",
    "han_viet": "GIANG HỘ THỜI ĐẠI",
    "kana": "えどじだい",
    "romaji": "edojidai",
    "tags": [
      "n4",
      "noun",
      "history"
    ],
    "pitch_pattern": 3,
    "pitch_svg_path": "M0,20 L25,5 L50,5 L75,20 L100,20",
    "etymology": {
      "parts": [
        {
          "kanji": "江",
          "han_viet": "GIANG",
          "meaning": {
            "vi": "sông",
            "en": "inlet"
          }
        },
        {
          "kanji": "戸",
          "han_viet": "HỘ",
          "meaning": {
            "vi": "cửa",
            "en": "door"
          }
        },
        {
          "kanji": "時",
          "han_viet": "THỜI",
          "meaning": {
            "vi": "thời gian",
            "en": "time"
          }
        },
        {
          "kanji": "代",
          "han_viet": "ĐẠI",
          "meaning": {
            "vi": "thế hệ",
            "en": "era"
          }
        }
      ],
      "note": {
        "vi": "Thời đại Edo.",
        "en": "Edo Period."
      }
    },
    "meanings": {
      "vi": [
        "Thời đại Edo (1603-1868)"
      ],
      "en": [
        "Edo Period"
      ]
    },
    "examples": [
      {
        "sentence": "江戸時代について勉強します。",
        "translation": {
          "vi": "Học về thời đại Edo.",
          "en": "Study about the Edo Period."
        }
      }
    ],
    "mnemonic": {
      "vi": "GIANG HỘ THỜI ĐẠI.",
      "en": "Edo Jedi (Jidai)."
    },
    "confusions": []
  },
  {
    "word_surface": "皆様",
    "han_viet": "GIAI DẠNG",
    "kana": "みなさま",
    "romaji": "minasama",
    "tags": [
      "n4",
      "noun",
      "polite"
    ],
    "pitch_pattern": 2,
    "pitch_svg_path": "M0,20 L25,5 L50,20 L75,20",
    "etymology": {
      "parts": [
        {
          "kanji": "皆",
          "han_viet": "GIAI",
          "meaning": {
            "vi": "mọi người",
            "en": "everyone"
          }
        },
        {
          "kanji": "様",
          "han_viet": "DẠNG",
          "meaning": {
            "vi": "ngài",
            "en": "Mr/Ms"
          }
        }
      ],
      "note": {
        "vi": "Kính ngữ của minasan.",
        "en": "Everyone (Formal)."
      }
    },
    "meanings": {
      "vi": [
        "quý vị",
        "mọi người (kính ngữ)"
      ],
      "en": [
        "everyone",
        "ladies and gentlemen"
      ]
    },
    "examples": [
      {
        "sentence": "皆様、こんにちは。",
        "translation": {
          "vi": "Kính chào quý vị.",
          "en": "Hello everyone."
        }
      }
    ],
    "mnemonic": {
      "vi": "GIAI DẠNG.",
      "en": "Me, NASA ma (Minasama) - My mom is at NASA with everyone."
    },
    "confusions": []
  },
  {
    "word_surface": "焼けます",
    "han_viet": "THIÊU",
    "kana": "やけます",
    "romaji": "yakemasu",
    "tags": [
      "n4",
      "verb",
      "intransitive"
    ],
    "pitch_pattern": 2,
    "pitch_svg_path": "M0,20 L25,5 L50,20 L75,20",
    "etymology": {
      "parts": [
        {
          "kanji": "焼",
          "han_viet": "THIÊU",
          "meaning": {
            "vi": "đốt cháy",
            "en": "burn"
          }
        }
      ],
      "note": {
        "vi": "THIÊU (焼) trong thiêu dụi, nướng.",
        "en": "To burn."
      }
    },
    "meanings": {
      "vi": [
        "cháy (nhà)",
        "nướng (bánh)"
      ],
      "en": [
        "burn",
        "be baked"
      ]
    },
    "examples": [
      {
        "sentence": "家が焼けました。",
        "translation": {
          "vi": "Nhà bị cháy.",
          "en": "The house burned down."
        }
      }
    ],
    "mnemonic": {
      "vi": "THIÊU cháy mọi thứ.",
      "en": "Ya (Ya), Ke (Ke) - Yeah, 'kay, let it burn."
    },
    "confusions": []
  },
  {
    "word_surface": "その後",
    "han_viet": "HẬU",
    "kana": "そのご",
    "romaji": "sonogo",
    "tags": [
      "n4",
      "noun",
      "time"
    ],
    "pitch_pattern": 0,
    "pitch_svg_path": "M0,20 L25,5 L50,5",
    "etymology": {
      "parts": [
        {
          "kanji": "後",
          "han_viet": "HẬU",
          "meaning": {
            "vi": "sau",
            "en": "after"
          }
        }
      ],
      "note": {
        "vi": "Sau cái đó.",
        "en": "After that."
      }
    },
    "meanings": {
      "vi": [
        "sau đó"
      ],
      "en": [
        "after that"
      ]
    },
    "examples": [
      {
        "sentence": "その後、どうなりましたか。",
        "translation": {
          "vi": "Sau đó thì thế nào?",
          "en": "What happened after that?"
        }
      }
    ],
    "mnemonic": {
      "vi": "So no go (Sonogo).",
      "en": "So no go (Sonogo)."
    },
    "confusions": []
  }
]